openapi_pydantic_models/__init__.py
openapi_pydantic_models/commons/__init__.py
openapi_pydantic_models/commons/base_model.py
openapi_pydantic_models/commons/utilities.py
openapi_pydantic_models/openapi_3_1/__init__.py
openapi_pydantic_models/openapi_3_1/callback_object.py
openapi_pydantic_models/openapi_3_1/components_object.py
openapi_pydantic_models/openapi_3_1/contact_object.py
openapi_pydantic_models/openapi_3_1/encoding_object.py
openapi_pydantic_models/openapi_3_1/example_object.py
openapi_pydantic_models/openapi_3_1/external_documentation_object.py
openapi_pydantic_models/openapi_3_1/header_object.py
openapi_pydantic_models/openapi_3_1/info_object.py
openapi_pydantic_models/openapi_3_1/license_object.py
openapi_pydantic_models/openapi_3_1/link_object.py
openapi_pydantic_models/openapi_3_1/locations.py
openapi_pydantic_models/openapi_3_1/media_type_object.py
openapi_pydantic_models/openapi_3_1/oauth_flow_object.py
openapi_pydantic_models/openapi_3_1/oauth_flows_object.py
openapi_pydantic_models/openapi_3_1/openapi_object.py
openapi_pydantic_models/openapi_3_1/operation_object.py
openapi_pydantic_models/openapi_3_1/parameter_object.py
openapi_pydantic_models/openapi_3_1/path_item_object.py
openapi_pydantic_models/openapi_3_1/paths_object.py
openapi_pydantic_models/openapi_3_1/reference_object.py
openapi_pydantic_models/openapi_3_1/request_body_object.py
openapi_pydantic_models/openapi_3_1/response_object.py
openapi_pydantic_models/openapi_3_1/responses_object.py
openapi_pydantic_models/openapi_3_1/schema_object.py
openapi_pydantic_models/openapi_3_1/security_requirement_object.py
openapi_pydantic_models/openapi_3_1/security_scheme_object.py
openapi_pydantic_models/openapi_3_1/server_object.py
openapi_pydantic_models/openapi_3_1/server_variable_object.py
openapi_pydantic_models/openapi_3_1/specification_extensions.py
openapi_pydantic_models/openapi_3_1/styles.py
openapi_pydantic_models/openapi_3_1/tag_object.py
openapi_pydantic_models-1.0.1.dist-info/LICENSE
openapi_pydantic_models-1.0.1.dist-info/METADATA
openapi_pydantic_models-1.0.1.dist-info/WHEEL
openapi_pydantic_models-1.0.1.dist-info/top_level.txt
openapi_pydantic_models-1.0.1.dist-info/RECORD
