Metadata-Version: 2.1
Name: openapi-pydantic-models
Version: 1.0.1
Summary: pydantic models for OpeanAPI Specification 3.1.0 objects.
Author-email: Tomislav Adamic <tomislav.adamic@gmail.com>
License: MIT
Project-URL: Source, https://github.com/tadams42/openapi-pydantic-models
Keywords: OpenAPI OAS
Platform: any
Classifier: Development Status :: 5 - Production/Stable
Classifier: License :: OSI Approved :: MIT License
Classifier: Operating System :: POSIX :: Linux
Classifier: Programming Language :: Python
Classifier: Programming Language :: Python :: 3
Classifier: Programming Language :: Python :: 3.10
Classifier: Programming Language :: Python :: 3.11
Classifier: Programming Language :: Python :: 3 :: Only
Requires-Python: >=3.10
License-File: LICENSE
Requires-Dist: pydantic (>=2.0)
Provides-Extra: dev
Requires-Dist: ipython (>=8.6.0) ; extra == 'dev'
Requires-Dist: black (>=22.1.0) ; extra == 'dev'
Requires-Dist: bump2version (>=1.0.1) ; extra == 'dev'
Requires-Dist: check-manifest (>=0.47) ; extra == 'dev'
Requires-Dist: isort (>=5.10.1) ; extra == 'dev'
Requires-Dist: pip-tools (>=6.5.1) ; extra == 'dev'
Requires-Dist: rich ; extra == 'dev'
Requires-Dist: requests ; extra == 'dev'
Requires-Dist: pyyaml ; extra == 'dev'
Provides-Extra: docs
Requires-Dist: furo ; extra == 'docs'
Requires-Dist: myst-parser ; extra == 'docs'
Requires-Dist: sphinx (>5.2.0) ; extra == 'docs'
Requires-Dist: sphinx-rtd-theme ; extra == 'docs'
Requires-Dist: sphinx-copybutton ; extra == 'docs'
Provides-Extra: tests
Requires-Dist: coverage ; extra == 'tests'
Requires-Dist: factory-boy (>=3.2.1) ; extra == 'tests'
Requires-Dist: faker (>=12.3.0) ; extra == 'tests'
Requires-Dist: lorem (>=0.1.1) ; extra == 'tests'
Requires-Dist: pytest (>=7.0.1) ; extra == 'tests'
Requires-Dist: pytest-spec (>=3.2.0) ; extra == 'tests'
Requires-Dist: pytest-profiling (>=1.7.0) ; extra == 'tests'
Requires-Dist: pytest-random-order (>=1.0.4) ; extra == 'tests'
Requires-Dist: pyyaml ; extra == 'tests'
